proventosweb/__init__.py
proventosweb/proventosweb.py
proventosweb-0.84.dist-info/METADATA
proventosweb-0.84.dist-info/WHEEL
proventosweb-0.84.dist-info/top_level.txt
proventosweb-0.84.dist-info/RECORD
