Metadata-Version: 2.1
Name: proventosweb
Version: 0.84
Summary: Uma biblioteca para buscar proventos de ações na plataforma Status Invest
Home-page: https://github.com/rafaelpsampaio/proventosweb
Author: Rafael Sampaio
Author-email: rafapsampaio@gmail.com
License: UNKNOWN
Platform: UNKNOWN
Requires-Dist: pandas
Requires-Dist: datetime
Requires-Dist: requests
Requires-Dist: bs4
Requires-Dist: numpy
